django_pixels/__init__.py
django_pixels/apps.py
django_pixels/const.py
django_pixels/exceptions.py
django_pixels/handlers.py
django_pixels/models.py
django_pixels/urls.py
django_pixels/utils.py
django_pixels/views.py
django_pixels-0.2.dist-info/DESCRIPTION.rst
django_pixels-0.2.dist-info/METADATA
django_pixels-0.2.dist-info/RECORD
django_pixels-0.2.dist-info/WHEEL
django_pixels-0.2.dist-info/metadata.json
django_pixels-0.2.dist-info/top_level.txt
