Metadata-Version: 2.0
Name: django-pixels
Version: 0.2
Summary: Tracking pixels made easy
Home-page: https://github.com/kasun/django-pixels
Author: Kasun Herath
Author-email: kasunh01@gmail.com
License: MIT
Keywords: django_pixels
Platform: UNKNOWN
Classifier: Development Status :: 3 - Alpha
Classifier: Framework :: Django
Classifier: Framework :: Django :: 1.8
Classifier: Framework :: Django :: 1.9
Classifier: Framework :: Django :: 1.10
Classifier: Intended Audience :: Developers
Classifier: License :: OSI Approved :: BSD License
Classifier: Natural Language :: English
Classifier: Programming Language :: Python :: 2
Classifier: Programming Language :: Python :: 2.7
